analyzer/__init__.py
analyzer/base.py
analyzer/conflicts.py
analyzer/dead_locations.py
analyzer/diff.py
analyzer/duplicates.py
analyzer/empty_blocks.py
analyzer/include.py
analyzer/rewrite.py
analyzer/route.py
analyzer/unused.py
analyzer/warnings.py
commands/__init__.py
commands/analyze.py
commands/cli.py
commands/diff.py
commands/graph.py
commands/health.py
commands/include.py
commands/logs.py
commands/resolve.py
commands/route.py
commands/syntax.py
commands/tree.py
exporter/__init__.py
exporter/graph.py
exporter/html.py
exporter/markdown.py
nginx_lens-0.3.3.dist-info/licenses/LICENSE
parser/__init__.py
parser/nginx_parser.py
upstream_checker/__init__.py
upstream_checker/checker.py
nginx_lens-0.3.3.dist-info/METADATA
nginx_lens-0.3.3.dist-info/WHEEL
nginx_lens-0.3.3.dist-info/entry_points.txt
nginx_lens-0.3.3.dist-info/top_level.txt
nginx_lens-0.3.3.dist-info/RECORD
