Metadata-Version: 2.4
Name: nginx-lens
Version: 0.3.3
Summary: CLI-инструмент для анализа, визуализации и диагностики конфигураций Nginx
Author: Daniil Astrouski
Author-email: shelovesuastra@gmail.com
Requires-Python: >=3.8
License-File: LICENSE
Requires-Dist: typer[all]>=0.9.0
Requires-Dist: rich>=13.0.0
Requires-Dist: requests>=2.25.0
Requires-Dist: dnspython>=2.0.0
Dynamic: author
Dynamic: author-email
Dynamic: license-file
Dynamic: requires-dist
Dynamic: requires-python
Dynamic: summary
